odoo/addons/sale_order_priority/README.rst
odoo/addons/sale_order_priority/__init__.py
odoo/addons/sale_order_priority/__manifest__.py
odoo/addons/sale_order_priority/i18n/it.po
odoo/addons/sale_order_priority/i18n/sale_order_priority.pot
odoo/addons/sale_order_priority/models/__init__.py
odoo/addons/sale_order_priority/models/sale.py
odoo/addons/sale_order_priority/readme/CONTRIBUTORS.rst
odoo/addons/sale_order_priority/readme/DESCRIPTION.rst
odoo/addons/sale_order_priority/static/description/icon.png
odoo/addons/sale_order_priority/static/description/index.html
odoo/addons/sale_order_priority/tests/__init__.py
odoo/addons/sale_order_priority/tests/test_sale_stock.py
odoo/addons/sale_order_priority/views/sale.xml
odoo13_addon_sale_order_priority-13.0.1.0.1.dev6.dist-info/METADATA
odoo13_addon_sale_order_priority-13.0.1.0.1.dev6.dist-info/WHEEL
odoo13_addon_sale_order_priority-13.0.1.0.1.dev6.dist-info/top_level.txt
odoo13_addon_sale_order_priority-13.0.1.0.1.dev6.dist-info/RECORD
